{
    "intents":[ {"tag":"Axis Deer","pattern":["speciescommand","Axis Deer","axis","deer"],"response":["axisdeer"]},
                {"tag":"Beceite Ibex","pattern":["speciescommand","Beceite Ibex","beceite","ibex"],"response":["beceiteibex"]},
                {"tag":"Bighorn Sheep","pattern":["speciescommand","Bighorn Sheep","big","horn","sheep","bighorn"],"response":["bighornsheep"]},
                {"tag":"Black Bear","pattern":["speciescommand","Black Bear","black","bear"],"response":["blackbear"]},
                {"tag":"Blackbuck","pattern":["speciescommand","Blackbuck","black","buck","blackbuck"],"response":["blackbuck"]},
                {"tag":"Blacktail Deer","pattern":["speciescommand","Blacktail Deer","black","tail","deer","blacktail"],"response":["blacktaildeer"]},
                {"tag":"Blue Wildebeest","pattern":["speciescommand","Blue Wildebeest","blue","wilde","beest","beast","wild","wildebeest","wildebeast"],"response":["bluewildebeest"]},
                {"tag":"Brown Bear","pattern":["speciescommand","Brown Bear","brown","bear","eurasian","asian"],"response":["canadagoose"]},
                {"tag":"Canada Goose","pattern":["speciescommand","Canada Goose","canada","goose","geese","canadian"],"response":["capebuffalo"]},
                {"tag":"Cape Buffalo","pattern":["speciescommand","Cape Buffalo","cape","buffalo"],"response":["caribou"]},
                {"tag":"Caribou","pattern":["speciescommand","Caribou","caribou"],"response":["chamois"]},
                {"tag":"Chamois","pattern":["speciescommand","Chamois","chamois"],"response":["cinnamonteal"]},
                {"tag":"Cinnamon Teal","pattern":["speciescommand","Cinnamon Teal","cinnamon","teal"],"response":["coyote"]},
                {"tag":"Coyote","pattern":["speciescommand","Coyote","coyote"],"response":["eurasianbrownbear"]},
                {"tag":"Eurasian Lynx","pattern":["speciescommand","Eurasian Lynx","eurasian","lynx","asian"],"response":["eurasianlynx"]},
                {"tag":"European Bison","pattern":["speciescommand","European Bison","european","bison","europe"],"response":["europeanbison"]},
                {"tag":"European Hare","pattern":["speciescommand","European Hare","european","hare","europe"],"response":["europeanhare"]},
                {"tag":"European Rabbit","pattern":["speciescommand","European Rabbit","european","rabbit","europe"],"response":["europeanrabbit"]},
                {"tag":"Fallow Deer","pattern":["speciescommand","Fallow Deer","fallow","deer"],"response":["fallowdeer"]},
                {"tag":"Feral Goat","pattern":["speciescommand","Feral Goat","feral","goat"],"response":["feralgoat"]},
                {"tag":"Feral Pig","pattern":["speciescommand","Feral Pig","feral","pig","hog"],"response":["feralpig"]},
                {"tag":"Gemsbok","pattern":["speciescommand","Gemsbok","gems","bok","gemsbok"],"response":["gemsbok"]},
                {"tag":"Gredos Ibex","pattern":["speciescommand","Gredos Ibex","gredos","ibex","gredo"],"response":["graywolf"]},
                {"tag":"Grey Wolf","pattern":["speciescommand","Grey Wolf","grey","wolf","wolves","gray"],"response":["gredosibex"]},
                {"tag":"Grizzly Bear","pattern":["speciescommand","Grizzly Bear","grizzly","bear","grizzlie"],"response":["grizzlybear"]},
                {"tag":"Harlequin Duck","pattern":["speciescommand","Harlequin Duck","harlequin","duck","harley","harle","quin"],"response":["harlequinduck"]},
                {"tag":"Iberian Mouflon","pattern":["speciescommand","Iberian Mouflon","iberian","mou","flon","mouflon"],"response":["iberianmouflon"]},
                {"tag":"Iberian Wolf","pattern":["speciescommand","Iberian Wolf","iberian","wolf","wolves"],"response":["iberianwolf"]},
                {"tag":"Jackrabbit","pattern":["speciescommand","Jackrabbit","jack","rabbit","jackrabbit"],"response":["jackrabbit"]},
                {"tag":"Lesser Kudu","pattern":["speciescommand","Lesser Kudu","lesser","kudu"],"response":["lesserkudu"]},
                {"tag":"Lion","pattern":["speciescommand","Lion","lion","lioness"],"response":["lion"]},
                {"tag":"Mallard","pattern":["speciescommand","Mallard","mallard"],"response":["mallard"]},
                {"tag":"Moose","pattern":["speciescommand","Moose","moose"],"response":["moose"]},
                {"tag":"Mountain Goat","pattern":["speciescommand","Mountain Goat","mountain","goat"],"response":["mountaingoat"]},
                {"tag":"Mountain Lion","pattern":["speciescommand","Mountain Lion","mountain","lion"],"response":["mountainlion"]},
                {"tag":"Mule Deer","pattern":["speciescommand","Mule Deer","mule","deer"],"response":["muledeer"]},
                {"tag":"Musk Deer","pattern":["speciescommand","Musk Deer","musk","deer"],"response":["plainsbison"]},
                {"tag":"Plains Bison","pattern":["speciescommand","Plains Bison","plains","bison"],"response":["pronghorn"]},
                {"tag":"Pronghorn","pattern":["speciescommand","Pronghorn","prong","horn","pronghorn"],"response":["puma"]},
                {"tag":"Puma","pattern":["speciescommand","Puma","puma"],"response":["reddeer"]},
                {"tag":"Red Deer","pattern":["speciescommand","Red Deer","red","deer","reddeer"],"response":["redfox"]},
                {"tag":"Red Fox","pattern":["speciescommand","Red Fox","red","fox"],"response":["reindeer"]},
                {"tag":"Reindeer","pattern":["speciescommand","Reindeer","rein","deer","rain","reindeer","raindeer"],"response":["rockymountainelk"]},
                {"tag":"Rocky Mountain Elk","pattern":["speciescommand","Rocky Mountain Elk","rocky","mountain","elk","rockymountain"],"response":["roedeer"]},
                {"tag":"Roe Deer","pattern":["speciescommand","Roe Deer","roe","deer","roedeer"],"response":["rondaibex"]},
                {"tag":"Ronda Ibex","pattern":["speciescommand","Ronda Ibex","ronda","ibez"],"response":["rooseveltelk"]},
                {"tag":"Roosevelt Elk","pattern":["speciescommand","Roosevelt Elk","roosevelt","elk"],"response":["scrubhare"]},
                {"tag":"Scrub Hare","pattern":["speciescommand","Scrub Hare","scrub","hare","scrubhare"],"response":["siberianmuskdeer"]},
                {"tag":"Side-Striped Jackal","pattern":["speciescommand","Side-Striped Jackal","side","striped","jackal","sidestriped"],"response":["side-stripedjackal"]},
                {"tag":"Sika Deer","pattern":["speciescommand","Sika Deer","sika","deer"],"response":["sikadeer"]},
                {"tag":"Southeastern Ibex","pattern":["speciescommand","Southeastern Ibex","south","eastern","ibex","southeastern"],"response":["southeasternspanishibex"]},
                {"tag":"Springbok","pattern":["speciescommand","Springbok","spring","bok","springbok"],"response":["springbok"]},
                {"tag":"Turkey","pattern":["speciescommand","Turkey","turkey"],"response":["turkey"]},
                {"tag":"Warthog","pattern":["speciescommand","Warthog","wart","hog","warthog"],"response":["warthog"]},
                {"tag":"Water Buffalo","pattern":["speciescommand","Water Buffalo","water","buffalo"],"response":["waterbuffalo"]},
                {"tag":"Whitetail Deer","pattern":["speciescommand","Whitetail Deer","white","tail","deer","whitetail"],"response":["whitetaildeer"]},
                {"tag":"Wild Boar","pattern":["speciescommand","Wild Boar","wild","boar"],"response":["wildboar"]}
    ]
}